typer_tools/__init__.py
typer_tools/__init__.pyi
typer_tools/depends.py
typer_tools/options.py
typer_tools-0.1.2.dist-info/METADATA
typer_tools-0.1.2.dist-info/WHEEL
typer_tools-0.1.2.dist-info/top_level.txt
typer_tools-0.1.2.dist-info/RECORD
